pygeom/__init__.py
pygeom/geom1d/__init__.py
pygeom/geom1d/cubicspline1d.py
pygeom/geom1d/linearspline1d.py
pygeom/geom2d/__init__.py
pygeom/geom2d/beziercurve2d.py
pygeom/geom2d/circle2d.py
pygeom/geom2d/coordinate2d.py
pygeom/geom2d/cubicspline2d.py
pygeom/geom2d/infiniteline2d.py
pygeom/geom2d/line2d.py
pygeom/geom2d/nurbscurve2d.py
pygeom/geom2d/nurbssurface2d.py
pygeom/geom2d/paramcurve2d.py
pygeom/geom2d/paramsurface2d.py
pygeom/geom2d/point2d.py
pygeom/geom2d/spline2d.py
pygeom/geom2d/tensor2d.py
pygeom/geom2d/transform2d.py
pygeom/geom2d/vector2d.py
pygeom/geom3d/__init__.py
pygeom/geom3d/beziercurve.py
pygeom/geom3d/beziersurface.py
pygeom/geom3d/circle.py
pygeom/geom3d/coordinate.py
pygeom/geom3d/cubicspline.py
pygeom/geom3d/infiniteline3d.py
pygeom/geom3d/line.py
pygeom/geom3d/lines.py
pygeom/geom3d/nurbscurve.py
pygeom/geom3d/nurbssurface.py
pygeom/geom3d/paramcurve.py
pygeom/geom3d/paramsurface.py
pygeom/geom3d/plane.py
pygeom/geom3d/point.py
pygeom/geom3d/spline.py
pygeom/geom3d/tools.py
pygeom/geom3d/transform.py
pygeom/geom3d/triangles.py
pygeom/geom3d/vector.py
pygeom/interp1d/__init__.py
pygeom/interp1d/linearinterp.py
pygeom/interp1d/quadraticinterp.py
pygeom/symbol2d/__init__.py
pygeom/symbol2d/symbolicvector2d.py
pygeom/symbol3d/__init__.py
pygeom/symbol3d/symbolicvector.py
pygeom/tools/__init__.py
pygeom/tools/basis.py
pygeom/tools/bernstein.py
pygeom/tools/fits.py
pygeom/tools/k3d.py
pygeom/tools/mesh.py
pygeom/tools/mpl.py
pygeom/tools/roots.py
pygeom/tools/solvers.py
pygeom/tools/spacing.py
pygeom-0.0.14.dist-info/licenses/LICENSE
pygeom-0.0.14.dist-info/METADATA
pygeom-0.0.14.dist-info/WHEEL
pygeom-0.0.14.dist-info/top_level.txt
pygeom-0.0.14.dist-info/RECORD
