Metadata-Version: 2.4
Name: pygeom
Version: 0.0.14
Summary: Python Package for Geometry
Author-email: Xero64 <xero64@gmail.com>
License-Expression: MIT
Project-URL: Homepage, https://github.com/Xero64/pygeom
Project-URL: Issues, https://github.com/Xero64/pygeom/issues
Classifier: Programming Language :: Python :: 3
Classifier: Operating System :: OS Independent
Requires-Python: >=3.10
License-File: LICENSE
Requires-Dist: matplotlib>=3.10.5
Requires-Dist: numpy>=2.2.6
Requires-Dist: sympy>=1.14.0
Dynamic: license-file
